funpdbe_validator/__init__.py
funpdbe_validator/residue_index.py
funpdbe_validator/validator.py
funpdbe_validator-1.1.3.dist-info/LICENSE
funpdbe_validator-1.1.3.dist-info/METADATA
funpdbe_validator-1.1.3.dist-info/WHEEL
funpdbe_validator-1.1.3.dist-info/top_level.txt
funpdbe_validator-1.1.3.dist-info/zip-safe
funpdbe_validator-1.1.3.dist-info/RECORD
