Metadata-Version: 2.1
Name: funpdbe-validator
Version: 1.1.3
Summary: Validate PDBe-KB JSONs by FunPDBe Schema
Home-page: https://github.com/PDBe-KB/funpdbe-validator
Author: Mihaly Varadi
Author-email: mvaradi@ebi.ac.uk
Keywords: json funpdbe_validator
Classifier: Programming Language :: Python :: 3
Classifier: Operating System :: OS Independent
Requires-Python: >=3.6
License-File: LICENSE
Requires-Dist: jsonschema
Requires-Dist: requests
Requires-Dist: gemmi
